hexstrike_ai/__init__.py
hexstrike_ai/__main__.py
hexstrike_ai/agents/__init__.py
hexstrike_ai/agents/ai_payload_generator.py
hexstrike_ai/agents/browser_agent.py
hexstrike_ai/agents/bugbounty/__init__.py
hexstrike_ai/agents/bugbounty/workflow_manager.py
hexstrike_ai/agents/ctf/__init__.py
hexstrike_ai/agents/ctf/automator.py
hexstrike_ai/agents/ctf/coordinator.py
hexstrike_ai/agents/ctf/workflow_manager.py
hexstrike_ai/agents/cve/__init__.py
hexstrike_ai/agents/cve/correlator.py
hexstrike_ai/agents/cve/exploit_ai.py
hexstrike_ai/agents/cve/exploits/__init__.py
hexstrike_ai/agents/cve/exploits/auth_bypass.py
hexstrike_ai/agents/cve/exploits/buffer_overflow.py
hexstrike_ai/agents/cve/exploits/deserial.py
hexstrike_ai/agents/cve/exploits/file_read.py
hexstrike_ai/agents/cve/exploits/generic.py
hexstrike_ai/agents/cve/exploits/rce.py
hexstrike_ai/agents/cve/exploits/sqli.py
hexstrike_ai/agents/cve/exploits/xss.py
hexstrike_ai/agents/cve/exploits/xxe.py
hexstrike_ai/agents/cve/intelligence_manager.py
hexstrike_ai/agents/decision_engine.py
hexstrike_ai/api/__init__.py
hexstrike_ai/api/routes/__init__.py
hexstrike_ai/api/routes/ai.py
hexstrike_ai/api/routes/bugbounty.py
hexstrike_ai/api/routes/core.py
hexstrike_ai/api/routes/ctf.py
hexstrike_ai/api/routes/error_handling.py
hexstrike_ai/api/routes/files.py
hexstrike_ai/api/routes/intelligence.py
hexstrike_ai/api/routes/process_workflows.py
hexstrike_ai/api/routes/processes.py
hexstrike_ai/api/routes/python_env.py
hexstrike_ai/api/routes/tools_api.py
hexstrike_ai/api/routes/tools_binary.py
hexstrike_ai/api/routes/tools_cloud.py
hexstrike_ai/api/routes/tools_exploit.py
hexstrike_ai/api/routes/tools_forensics.py
hexstrike_ai/api/routes/tools_network.py
hexstrike_ai/api/routes/tools_parameters.py
hexstrike_ai/api/routes/tools_web.py
hexstrike_ai/api/routes/tools_web_advanced.py
hexstrike_ai/api/routes/tools_web_frameworks.py
hexstrike_ai/api/routes/visual.py
hexstrike_ai/api/routes/vuln_intel.py
hexstrike_ai-0.1.0.dist-info/WHEEL
hexstrike_ai-0.1.0.dist-info/METADATA
hexstrike_ai-0.1.0.dist-info/RECORD
