Metadata-Version: 2.3
Name: hexstrike-ai
Version: 0.1.0
Summary: hexstrike-ai， 
Requires-Dist: aiohttp>=3.8.0,<4.0.0
Requires-Dist: angr>=9.2.0,<10.0.0
Requires-Dist: bcrypt==4.0.1
Requires-Dist: beautifulsoup4>=4.12.0,<5.0.0
Requires-Dist: fastmcp>=0.2.0,<1.0.0
Requires-Dist: flask>=2.3.0,<4.0.0
Requires-Dist: mitmproxy>=9.0.0,<11.0.0
Requires-Dist: psutil>=5.9.0,<6.0.0
Requires-Dist: pwntools>=4.10.0,<5.0.0
Requires-Dist: requests>=2.31.0,<3.0.0
Requires-Dist: selenium>=4.15.0,<5.0.0
Requires-Dist: webdriver-manager>=4.0.0,<5.0.0
Requires-Python: >=3.13
